setup.py
gdtools/__init__.py
gdtools/authpolicy.py
gdtools/gdtools_scripts.py
gdtools/login.py
gdtools.egg-info/PKG-INFO
gdtools.egg-info/SOURCES.txt
gdtools.egg-info/dependency_links.txt
gdtools.egg-info/entry_points.txt
gdtools.egg-info/not-zip-safe
gdtools.egg-info/requires.txt
gdtools.egg-info/top_level.txt