Metadata-Version: 1.1
Name: gdtools
Version: 0.1.0
Summary: GeneDock command-line client for interacting with GeneDock platform
Home-page: https://www.genedock.com
Author: Wu Yarong
Author-email: wuyarong@genedock.com
License: UNKNOWN
Platform: UNKNOWN
Classifier: Intended Audience :: Developers
Classifier: Operating System :: OS Independent
Classifier: Programming Language :: Python
Classifier: Programming Language :: Python :: 2
Classifier: Programming Language :: Python :: 2.6
Classifier: Programming Language :: Python :: 2.7
Classifier: Programming Language :: Python :: 3
Classifier: Programming Language :: Python :: 3.3
Classifier: Programming Language :: Python :: 3.4
Classifier: Programming Language :: Python :: 3.5
